DarijaTranslatorAssistant/__initi__.py
DarijaTranslatorAssistant/darija_assistant.py
DarijaTranslatorAssistant/llm_client.py
DarijaTranslatorAssistant-1.0.1.dist-info/LICENSE
DarijaTranslatorAssistant-1.0.1.dist-info/METADATA
DarijaTranslatorAssistant-1.0.1.dist-info/WHEEL
DarijaTranslatorAssistant-1.0.1.dist-info/top_level.txt
DarijaTranslatorAssistant-1.0.1.dist-info/RECORD
