Metadata-Version: 2.1
Name: DarijaTranslatorAssistant
Version: 1.0.1
Summary: A library for assisting in translating Darija to English. It provides a list of potential translations for a given darija word. It also supports translation of full sentences using LLMs (e.g., OpenAI).
Home-page: https://github.com/aissam-out/DarijaTranslatorAssistant
Author: Aissam Outchakoucht
Author-email: aissam.outchakoucht@gmail.com
Classifier: Development Status :: 5 - Production/Stable
Classifier: Intended Audience :: Developers
Classifier: License :: OSI Approved :: MIT License
Classifier: Programming Language :: Python :: 3
Classifier: Operating System :: OS Independent
Classifier: Topic :: Software Development :: Libraries :: Python Modules
Requires-Python: >=3.6
Requires-Dist: DarijaDistance==1.0.8
Requires-Dist: openai==1.43.0
Requires-Dist: requests==2.32.3
